{
    "options_menu": {
        "type": "array",
        "margin": "0",
        "content": [
            {
                "type": "itemgrid",
                "h_alignment": "center",
                "item_size": "120",
                "item_margin": "3,-40,3,-30",
                "rows": [
                    [ ],
                    [ ],
                    [ ],
                    [ ],
                    [ ],
                    [ "y_true" ],
                    [ "darkrooms_false", "bee_false" ],
                    [ "captain_skip", "dampe_shuffle" ],
                    [ "lamp_shuffle", "bracelet_skip" ],
                    [ "open_true", "barrier_start" ]
                ]
            }            
        ]
    }
}